html2text_rs_py-0.1.1.dist-info/METADATA
html2text_rs_py-0.1.1.dist-info/WHEEL
html2text_rs_py/__init__.py
html2text_rs_py/html2text_rs_py.cpython-311-darwin.so
html2text_rs_py-0.1.1.dist-info/RECORD
