Metadata-Version: 2.1
Name: html2text_rs_py
Version: 0.1.1
Classifier: Programming Language :: Rust
Classifier: Programming Language :: Python :: Implementation :: CPython
Classifier: Programming Language :: Python :: Implementation :: PyPy
Requires-Python: >=3.7
Project-URL: Source Code, https://github.com/mpr1255/html2text_rs_py
